{
  "destination": "Van Andel Arena",
  "validModes": [
    "drive",
    "rideshare",
    "transit",
    "micromobility",
    "shuttle",
    "bike"
  ],
  "modeLabels": {
    "drive": "driving",
    "rideshare": "Uber/Lyft",
    "transit": "The Rapid",
    "bike": "biking",
    "micromobility": "Lime",
    "walk": "walking",
    "shuttle": "DASH"
  },
  "costLabels": {
    "drive": "Willing to pay",
    "rideshare": "Willing to pay",
    "transit": "Willing to pay",
    "bike": "Willing to pay",
    "micromobility": "Willing to pay",
    "walk": "Willing to pay",
    "shuttle": "Willing to pay"
  },
  "defaults": {
    "flexibilityEarlyMins": 15,
    "flexibilityLateMins": 0,
    "people": 1,
    "walkMiles": 0.5,
    "parkingMins": 10,
    "costDollars": 10
  },
  "defaultCosts": {
    "micromobility": 4,
    "transit": 1.75,
    "rideshare": 15
  },
  "recommendations": {
    "drive+shuttle": {
      "noWalk": {
        "title": "No options available",
        "body": "You're driving and using DASH but not willing to walk any distance. Consider adjusting your walk distance to see recommendations.",
        "isNoOptions": true
      },
      "default": {
        "title": "Park farther, use DASH for last mile",
        "body": "Park in a less crowded area and take the free DASH shuttle to get closer to your destination.",
        "badge": "Time saver",
        "steps": [
          {
            "title": "Park farther from destination",
            "description": "Find parking away from the destination where spots are easier to find. Look for areas with less competition."
          },
          {
            "title": "Take the DASH shuttle",
            "description": "Walk to the nearest DASH stop and board the free downtown shuttle. Ride it to get closer to your destination."
          }
        ]
      }
    },
    "drive+transit": {
      "noWalk": {
        "title": "No options available",
        "body": "You're driving and taking transit but not willing to walk any distance. Consider adjusting your walk distance to see recommendations.",
        "isNoOptions": true
      },
      "default": {
        "title": "Park at Rapid stop, take transit",
        "body": "Park near a Rapid transit stop and take the bus to get closer to your destination.",
        "badge": "Cost saver",
        "steps": [
          {
            "title": "Park near a Rapid stop",
            "description": "Find parking near a Rapid transit stop. This area will have more available parking."
          },
          {
            "title": "Board The Rapid",
            "description": "Walk to the Rapid stop and board the bus. Ride to a stop that's within walking distance of your destination.",
            "linkTemplate": "https://www.google.com/maps/dir/?api=1&destination={destinationEncoded}&travelmode=transit",
            "linkText": "View transit route on Google Maps"
          }
        ]
      }
    },
    "drive+micromobility": {
      "noWalk": {
        "title": "No options available",
        "body": "You're driving and using micromobility but not willing to walk any distance. Consider adjusting your walk distance to see recommendations.",
        "isNoOptions": true
      },
      "default": {
        "title": "Park farther, use Lime for last mile",
        "body": "Park in a less crowded area and use a Lime scooter or bike for the final stretch.",
        "badge": "Flexible",
        "steps": [
          {
            "title": "Park farther from destination",
            "description": "Find parking away from the destination where spots are easier to find. Look for areas with less competition."
          },
          {
            "title": "Find and ride a Lime scooter or bike",
            "description": "Open the Lime app and locate the nearest available scooter or bike. Unlock it and ride directly to your destination."
          }
        ]
      }
    },
    "drive": {
      "noWalk": {
        "title": "No options available",
        "body": "You're driving but not willing to walk any distance. Consider adjusting your walk distance to see recommendations.",
        "isNoOptions": true
      },
      "noCost": {
        "title": "No options available",
        "body": "Parking meters are enforced Monday-Friday 8am-7pm. Since you're not willing to pay for parking, there are no options available during enforcement hours.",
        "isNoOptions": true
      },
      "meteredParking": {
        "title": "Park at metered street parking",
        "body": "Park at street meters near the arena ($1.25-$2.00 per half hour, typically 2-3 hour max). Meters are enforced Monday-Friday 8am-7pm.",
        "badge": "Affordable",
        "steps": [
          {
            "title": "Find metered parking",
            "description": "Look for parking meters on streets surrounding Van Andel Arena: Fulton Street, Ionia Avenue, Ottawa Avenue, Monroe Avenue, Pearl Street, and Louis Street. Meters are typically available within 0.2 miles of the arena.",
            "link": "https://www.google.com/maps/search/?api=1&query=metered+parking+near+Van+Andel+Arena,+Grand+Rapids,+MI",
            "linkText": "Find meters on Google Maps"
          },
          {
            "title": "Pay for parking",
            "description": "Pay using the Motu (Mobile GR) app, or at the meter using cash, credit/debit card, or mobile payment. Rates are $1.25-$2.00 per half hour in prime areas ($2.50-$4.00 per hour). Maximum duration is typically 2-3 hours (varies by location)."
          },
          {
            "title": "Walk to destination",
            "description": "Walk from your parking spot."
          }
        ],
        "alternate": {
          "title": "Find free street parking",
          "body": "Spend 15 minutes in traffic circling the area to find free street parking. Meters are not enforced on weekends (free all day), and free on weekdays before 8am and after 7pm.",
          "steps": [
            {
              "title": "Spend 15 minutes in traffic looking for free street parking",
              "description": "Circle the blocks looking for free street parking. Meters are not enforced on weekends (free all day), and free on weekdays before 8am and after 7pm. Enforcement hours are Monday-Friday 8am-7pm. Be aware of odd-even parking restrictions from November 1 to April 1. This may take 15+ minutes of driving in traffic.",
              "link": "https://www.google.com/maps/search/?api=1&query=street+parking+near+Van+Andel+Arena,+Grand+Rapids,+MI",
              "linkText": "View area on Google Maps"
            },
            {
              "title": "Park and walk",
              "description": "Once you find a spot, park and walk."
            }
          ]
        }
      },
      "affordableLot": {
        "title": "Park at affordable surface lot and walk",
        "body": "Park at a surface parking lot (around $8-$10 for 4 hours) within {walkMiles} miles and walk the rest of the way. Surface lots are cheaper than ramps (structured parking garages).",
        "badge": "Budget-friendly",
        "steps": [
          {
            "title": "Find affordable surface parking lot",
            "description": "Look for surface parking lots near Ottawa and Fulton streets, or Market Street Lot. Surface lots are open-air parking areas (not garages) and typically cost $8-$10 for 4 hours, cheaper than ramps.",
            "link": "https://www.google.com/maps/search/?api=1&query=parking+lot+near+Ottawa+and+Fulton,+Grand+Rapids,+MI",
            "linkText": "Find lots on Google Maps"
          },
          {
            "title": "Park and walk",
            "description": "Park your car and walk up to {walkMiles} miles."
          }
        ],
        "alternate": {
          "title": "Find free street parking",
          "body": "Spend 15 minutes in traffic circling the area to find free street parking. Meters are not enforced on weekends (free all day), and free on weekdays before 8am and after 7pm.",
          "steps": [
            {
              "title": "Spend 15 minutes in traffic looking for free street parking",
              "description": "Circle the blocks looking for free street parking. Meters are not enforced on weekends (free all day), and free on weekdays before 8am and after 7pm. Enforcement hours are Monday-Friday 8am-7pm. Be aware of odd-even parking restrictions from November 1 to April 1. This may take 15+ minutes of driving in traffic.",
              "link": "https://www.google.com/maps/search/?api=1&query=street+parking+near+Van+Andel+Arena,+Grand+Rapids,+MI",
              "linkText": "View area on Google Maps"
            },
            {
              "title": "Park and walk",
              "description": "Once you find a spot, park and walk up to {walkMiles} miles."
            }
          ]
        }
      },
      "freeStreet": {
        "title": "Find free street parking",
        "body": "Spend 15 minutes in traffic circling the area to find free street parking. Meters are free after 7 PM on weekdays and all day on weekends.",
        "badge": "Free",
        "isDiscouraged": true,
        "steps": [
          {
            "title": "Spend 15 minutes in traffic looking for free street parking",
            "description": "Circle the blocks looking for free street parking. Meters are not enforced on weekends (free all day), and free on weekdays before 8am and after 7pm. Enforcement hours are Monday-Friday 8am-7pm. Be aware of odd-even parking restrictions from November 1 to April 1. This may take 15+ minutes of driving in traffic.",
            "link": "https://www.google.com/maps/search/?api=1&query=street+parking+near+Van+Andel+Arena,+Grand+Rapids,+MI",
            "linkText": "View area on Google Maps"
          },
          {
            "title": "Park and walk",
            "description": "Once you find a spot, park and walk up to {walkMiles} miles."
          }
        ]
      },
      "cheaperGarage": {
        "title": "Park at city parking garage",
        "body": "Park at a city-owned parking garage (Monroe Center Ramp or Ottawa-Fulton Ramp) for $1.50 per hour, max $12. These are affordable structured garages within 0.2-0.3 miles of the arena.",
        "badge": "Budget-friendly",
        "steps": [
          {
            "title": "Park at Monroe Center Ramp or Ottawa-Fulton Ramp",
            "description": "Monroe Center Ramp (25 Monroe Center NW) is 0.3 miles from Van Andel Arena. Ottawa-Fulton Ramp (50 Ottawa Ave NW) is 0.2 miles away. Both charge $1.50 per hour with a maximum of $12. These city-owned garages offer good availability and are more affordable than premium ramps.",
            "link": "https://www.google.com/maps/search/?api=1&query=Monroe+Center+Ramp+or+Ottawa-Fulton+Ramp,+Grand+Rapids,+MI",
            "linkText": "Find garages on Google Maps"
          },
          {
            "title": "Walk to destination",
            "description": "Walk from the garage (0.2-0.3 miles)."
          }
        ],
        "alternate": {
          "title": "Park at affordable surface lot",
          "body": "Park at a surface parking lot (around $8-$10 for 4 hours) within {walkMiles} miles and walk the rest of the way. Surface lots are cheaper than garages but fill up quickly.",
          "steps": [
            {
              "title": "Find affordable surface parking lot",
              "description": "Look for surface parking lots near Ottawa and Fulton streets, or Market Street Lot. Surface lots are open-air parking areas (not garages) and typically cost $8-$10 for 4 hours.",
              "link": "https://www.google.com/maps/search/?api=1&query=parking+lot+near+Ottawa+and+Fulton,+Grand+Rapids,+MI",
              "linkText": "Find lots on Google Maps"
            },
            {
              "title": "Park and walk",
              "description": "Park your car and walk up to {walkMiles} miles."
            }
          ]
        }
      },
      "premiumRamp": {
        "title": "Park at premium parking garage",
        "body": "Park at a premium ramp (structured parking garage) close by (around $27-$30 for evening/events) for convenient access. Premium ramps like Arena Place Garage are directly across from the arena and often have better availability because people avoid the higher cost.",
        "badge": "Convenient",
        "steps": [
          {
            "title": "Park at Arena Place Garage or Studio Park Ramp",
            "description": "Arena Place Garage (130 Ionia Ave SW) is directly across from Van Andel Arena. Studio Park Ramp (123 Ionia Ave SW) is 0.1 miles away. Both are premium ramps operated by Ellis Parking, typically costing $27-$30 for evening/events (daytime max $27). These structured parking garages often have better availability because people avoid the higher cost.",
            "link": "https://www.google.com/maps/search/?api=1&query=Arena+Place+Garage+or+Studio+Park+Ramp,+Grand+Rapids,+MI",
            "linkText": "Find garages on Google Maps"
          },
          {
            "title": "Walk to destination",
            "description": "Walk from the garage (0-0.1 miles)."
          }
        ],
        "alternate": {
          "title": "Find free street parking",
          "body": "Spend 15 minutes in traffic circling the area to find free street parking. Meters are not enforced on weekends (free all day), and free on weekdays before 8am and after 7pm.",
          "steps": [
            {
              "title": "Spend 15 minutes in traffic looking for free street parking",
              "description": "Circle the blocks looking for free street parking. Meters are not enforced on weekends (free all day), and free on weekdays before 8am and after 7pm. Enforcement hours are Monday-Friday 8am-7pm. Be aware of odd-even parking restrictions from November 1 to April 1. This may take 15+ minutes of driving in traffic.",
              "link": "https://www.google.com/maps/search/?api=1&query=street+parking+near+Van+Andel+Arena,+Grand+Rapids,+MI",
              "linkText": "View area on Google Maps"
            },
            {
              "title": "Park and walk",
              "description": "Once you find a spot, park and walk."
            }
          ]
        }
      }
    },
    "transit+shuttle": {
      "noCost": {
        "title": "No options available",
        "body": "The Rapid fare is $1.75. Consider adjusting your budget to see recommendations.",
        "isNoOptions": true
      },
      "noWalk": {
        "title": "No options available",
        "body": "You're taking The Rapid and using DASH but not willing to walk any distance. Consider adjusting your walk distance to see recommendations.",
        "isNoOptions": true
      },
      "default": {
        "title": "Take Rapid, then DASH",
        "body": "Ride The Rapid to downtown, then use the free DASH shuttle to get closer to your destination.",
        "badge": "Efficient",
        "steps": [
          {
            "title": "Board The Rapid",
            "description": "Go to your nearest Rapid stop and board the bus. Ride to a downtown stop that's near a DASH connection point.",
            "linkTemplate": "https://www.google.com/maps/dir/?api=1&destination={destinationEncoded}&travelmode=transit",
            "linkText": "View transit route on Google Maps"
          },
          {
            "title": "Transfer to DASH",
            "description": "Get off The Rapid and walk to the nearest DASH stop. Board the free DASH shuttle and ride it closer to your destination."
          },
          {
            "title": "Walk to destination",
            "description": "Get off the DASH shuttle and walk the remaining distance to your destination."
          }
        ]
      }
    },
    "transit": {
      "noCost": {
        "title": "No options available",
        "body": "The Rapid fare is $1.75. Consider adjusting your budget to see recommendations.",
        "isNoOptions": true
      },
      "noWalk": {
        "title": "No options available",
        "body": "You're taking The Rapid but not willing to walk any distance. Consider adjusting your walk distance to see recommendations.",
        "isNoOptions": true
      },
      "default": {
        "title": "The Rapid + short walk",
        "body": "Plan your route to a Rapid stop near your destination. Avoid transfers if possible. After getting off, walk the remaining distance.",
        "badge": "Chill",
        "steps": [
          {
            "title": "Take The Rapid",
            "description": "Go to your nearest Rapid stop and board the bus. Ride to a stop near your destination. Avoid transfers if possible.",
            "linkTemplate": "https://www.google.com/maps/dir/?api=1&destination={destinationEncoded}&travelmode=transit",
            "linkText": "View transit route on Google Maps"
          },
          {
            "title": "Walk to destination",
            "description": "Get off The Rapid and walk the remaining distance to your destination."
          }
        ]
      }
    },
    "rideshare": {
      "noCost": {
        "title": "No options available",
        "body": "Rideshare services typically cost at least $10. Consider adjusting your budget to see recommendations.",
        "isNoOptions": true
      },
      "default": {
        "title": "Request a rideshare to your destination",
        "body": "Request an Uber or Lyft and get dropped off at your destination.",
        "badge": "Door-to-door",
        "steps": [
          {
            "title": "Request an Uber/Lyft",
            "description": "Open your Uber or Lyft app and request a ride. Set your destination and confirm the ride."
          },
          {
            "title": "Arrive at destination",
            "description": "Wait for your driver to arrive, then ride to your destination. The driver will drop you off as close as possible."
          }
        ]
      }
    },
    "micromobility": {
      "noCost": {
        "title": "No options available",
        "body": "Lime typically costs at least $4. Consider adjusting your budget to see recommendations.",
        "isNoOptions": true
      },
      "default": {
        "title": "Find and ride a Lime scooter or bike",
        "body": "Open the Lime app and find the nearest available scooter or bike. Unlock it and ride directly to your destination.",
        "badge": "On-demand",
        "steps": [
          {
            "title": "Find a Lime scooter or bike",
            "description": "Open the Lime app and locate the nearest available scooter or bike near your starting location."
          },
          {
            "title": "Ride to destination",
            "description": "Unlock the scooter or bike and ride directly to your destination."
          }
        ]
      }
    },
    "shuttle": {
      "noWalk": {
        "title": "No options available",
        "body": "You're using DASH but not willing to walk any distance. Consider adjusting your walk distance to see recommendations.",
        "isNoOptions": true
      },
      "default": {
        "title": "Take the DASH shuttle",
        "body": "Use the free DASH downtown shuttle to get closer to your destination, then walk the remaining distance.",
        "badge": "Free",
        "steps": [
          {
            "title": "Find a DASH stop",
            "description": "Locate the nearest DASH shuttle stop near your starting location."
          },
          {
            "title": "Board the DASH shuttle",
            "description": "Wait for the next DASH shuttle and board it. The shuttle is free and runs through downtown Grand Rapids."
          },
          {
            "title": "Walk to destination",
            "description": "Get off the DASH shuttle at a stop near your destination and walk the remaining distance."
          }
        ]
      }
    },
    "bike": {
      "default": {
        "title": "Bike to your destination and lock up nearby",
        "body": "Ride your bike to your destination. Find a bike rack or secure post near the entrance to lock up. This avoids parking entirely.",
        "badge": "No parking",
        "steps": [
          {
            "title": "Ride your bike to destination",
            "description": "Ride your bike to your destination."
          },
          {
            "title": "Lock up your bike",
            "description": "Find a bike rack or secure post near the entrance and lock up your bike."
          }
        ]
      }
    }
  },
  "linkTexts": {
    "viewTransitRoute": "View transit route on Google Maps",
    "findLots": "Find lots on Google Maps",
    "viewArea": "View area on Google Maps",
    "findRamps": "Find ramps on Google Maps",
    "openLink": "Open link"
  },
  "parking": {
    "premiumRamps": [
      {
        "name": "Arena Place Garage",
        "address": "130 Ionia Ave SW, Grand Rapids, MI 49503",
        "distance": "Directly across from Van Andel Arena",
        "pricing": {
          "daytime": "Max $27",
          "evening": "$27-$30",
          "events": "$27-$30"
        },
        "availability": "Often better availability due to higher cost",
        "operator": "Ellis Parking",
        "type": "Premium structured parking garage"
      },
      {
        "name": "Studio Park Ramp",
        "address": "123 Ionia Ave SW, Grand Rapids, MI 49503",
        "distance": "0.1 miles from Van Andel Arena",
        "pricing": {
          "daytime": "Max $27",
          "evening": "$27-$30",
          "events": "$27-$30"
        },
        "availability": "Good availability",
        "operator": "Ellis Parking",
        "type": "Structured parking garage"
      }
    ],
    "cityGarages": [
      {
        "name": "Monroe Center Ramp",
        "address": "25 Monroe Center NW, Grand Rapids, MI 49503",
        "distance": "0.3 miles from Van Andel Arena",
        "pricing": {
          "daytime": "$1.50/hour, max $12",
          "evening": "$1.50/hour, max $12",
          "events": "Event pricing may apply"
        },
        "availability": "Good availability",
        "operator": "City of Grand Rapids",
        "type": "City parking garage"
      },
      {
        "name": "Ottawa-Fulton Ramp",
        "address": "50 Ottawa Ave NW, Grand Rapids, MI 49503",
        "distance": "0.2 miles from Van Andel Arena",
        "pricing": {
          "daytime": "$1.50/hour, max $12",
          "evening": "$1.50/hour, max $12",
          "events": "Event pricing may apply"
        },
        "availability": "Good availability",
        "operator": "City of Grand Rapids",
        "type": "City parking garage"
      }
    ],
    "surfaceLots": [
      {
        "name": "Market Street Lot",
        "location": "Near Market Street and Ottawa",
        "distance": "0.2-0.4 miles from Van Andel Arena",
        "pricing": {
          "rate": "$8-$10 for 4 hours"
        },
        "availability": "Limited, fills up quickly",
        "type": "Surface parking lot"
      },
      {
        "name": "Ottawa and Fulton area lots",
        "location": "Near Ottawa and Fulton streets",
        "distance": "0.2-0.5 miles from Van Andel Arena",
        "pricing": {
          "rate": "$8-$10 for 4 hours"
        },
        "availability": "Limited, fills up quickly",
        "type": "Surface parking lot"
      }
    ],
    "meteredParking": [
      {
        "location": "Streets surrounding Van Andel Arena",
        "areas": [
          "Fulton Street (east and west of arena)",
          "Ionia Avenue (north and south of arena)",
          "Ottawa Avenue",
          "Monroe Avenue",
          "Pearl Street",
          "Louis Street"
        ],
        "distance": "0-0.2 miles from Van Andel Arena",
        "pricing": {
          "rate": "$1.25-$2.00 per half hour in prime areas",
          "hourlyRate": "$2.50-$4.00 per hour",
          "maxDuration": "2-3 hours (varies by location)",
          "enforcement": "Monday-Friday 8am-7pm",
          "free": "After 5pm or 6pm and on weekends (event rates may apply)"
        },
        "payment": "Motu (Mobile GR) app, cash, credit/debit cards, mobile payment apps",
        "availability": "Limited during events, better availability on weekdays",
        "type": "Street metered parking (Motu/Mobile GR)",
        "operator": "City of Grand Rapids - Motu (Mobile GR)",
        "note": "No free street parking available within 0.5 miles of Van Andel Arena during enforcement hours"
      }
    ],
    "notes": {
      "premiumRamps": "Premium ramps like Arena Place often have better availability because people avoid the higher cost ($27-$30). These are the most convenient options with structured parking, located directly across from or very close to Van Andel Arena.",
      "cityGarages": "City parking garages offer more affordable rates ($1.50/hour, max $12) and are good alternatives to premium ramps. They're typically 0.2-0.3 miles from Van Andel Arena and provide structured parking at a lower cost.",
      "surfaceLots": "Surface lots are affordable ($8-$10 for 4 hours) but fill up quickly, especially during events. They require more walking distance (0.2-0.5 miles from the arena).",
      "meteredParking": "Street meters (Motu/Mobile GR) are the most affordable paid option ($1.25-$2.00 per half hour, $2.50-$4.00 per hour) but have time limits (typically 2-3 hours) and limited availability during events. Meters are enforced Monday-Friday 8am-7pm, free after 5pm or 6pm and on weekends (event rates may apply). No free street parking is available within 0.5 miles of Van Andel Arena during enforcement hours."
    }
  }
}
